ACML/__init__.py
acml-0.2.4.dist-info/LICENSE
acml-0.2.4.dist-info/METADATA
acml-0.2.4.dist-info/WHEEL
acml-0.2.4.dist-info/RECORD
