Metadata-Version: 2.1
Name: acml
Version: 0.2.4
Summary: 
Home-page: https://github.com/brodycritchlow/ACML
License: MIT
Keywords: configuration,config,advanced,ACML
Author: Brody Critchlow
Author-email: brodycritchlow@gmail.com
Requires-Python: >=3.11,<4.0
Classifier: License :: OSI Approved :: MIT License
Classifier: Programming Language :: Python :: 3
Classifier: Programming Language :: Python :: 3.11
